README.rst
setup.py
vam/__init__.py
vam/environment.py
vam/launcher.py
vam/package.py
vam/vam.py
vam.egg-info/PKG-INFO
vam.egg-info/SOURCES.txt
vam.egg-info/dependency_links.txt
vam.egg-info/entry_points.txt
vam.egg-info/requires.txt
vam.egg-info/top_level.txt