Metadata-Version: 1.0
Name: vam
Version: 0.1.9
Summary: Virtualenv Application Manager
Home-page: https://github.com/milliams/vam
Author: Matt Williams
Author-email: matt@milliams.com
License: MIT
Platform: UNKNOWN
